barium/__init__.py
barium/cli.py
bariumssg-0.1.5.dist-info/licenses/LICENSE
bariumssg-0.1.5.dist-info/METADATA
bariumssg-0.1.5.dist-info/WHEEL
bariumssg-0.1.5.dist-info/entry_points.txt
bariumssg-0.1.5.dist-info/top_level.txt
bariumssg-0.1.5.dist-info/RECORD
