Metadata-Version: 2.4
Name: BariumSSG
Version: 0.1.5
Summary: A simple static site generator
Author-email: Gijs6 <gijs6@dupunkto.org>
License-Expression: Unlicense
Requires-Python: >=3.7
License-File: LICENSE
Requires-Dist: jinja2
Requires-Dist: pyyaml
Requires-Dist: commonmark
Requires-Dist: markdown-it-py
Dynamic: license-file
